[{"ActivityName":"Rafraction","BrandName":"ALBA","ClaimTo":"pandurasa","CreatedBy":"kingkin","CreatedDate":"2025-05-20T10:25:45Z","Credit":0,"Creditx":0,"EndDatePeriode":"2025-06-05T00:00:00Z","Group":"HERO GROUP","GroupName":"HERO GROUP","Management":"management - 2025-05-28","Number":"PK010202510479","Realisasi":0,"Reff":"102/02510479","StartDatePeriode":"2025-05-23T00:00:00Z","Status":"approved","TotalCosting":4473300,"TotalCosting2":4473300,"id":16841,"jml_skp":1,"jnbalikkan":null,"klaimable":"N","lampiran":0}]